xy_django_app_resource/__init__.py
xy_django_app_resource/abstracts.py
xy_django_app_resource/admin.py
xy_django_app_resource/apps.py
xy_django_app_resource/models.py
xy_django_app_resource/serializers.py
xy_django_app_resource/tests.py
xy_django_app_resource/views.py
xy_django_app_resource/migrations/__init__.py
xy_django_app_resource-1.0.3.dist-info/LICENSE
xy_django_app_resource-1.0.3.dist-info/METADATA
xy_django_app_resource-1.0.3.dist-info/WHEEL
xy_django_app_resource-1.0.3.dist-info/top_level.txt
xy_django_app_resource-1.0.3.dist-info/RECORD
