Metadata-Version: 2.1
Name: xy_django_app_resource
Version: 1.0.3
Summary: 资源数据模型
Author-email: 余洋 <yuyangit.0515@qq.com>
Classifier: Programming Language :: Python :: 3
Requires-Python: >=3.11.3
License-File: LICENSE
Requires-Dist: django
Requires-Dist: djangorestframework
Requires-Dist: xy-type
Requires-Dist: xy-string
Requires-Dist: xy-django-model
Requires-Dist: xy-django-serializer
Requires-Dist: xy-django-app-information
